<?xml version="1.0" encoding="us-ascii"?>
<MQSim_Results>
	<Host>
		<Host.IO_Flow>
				 <Name>Host.IO_Flow.Trace.traces/tpcc-small.trace</Name>
				 <Request_Count>6999</Request_Count>
				 <Read_Request_Count>4381</Read_Request_Count>
				 <Write_Request_Count>2618</Write_Request_Count>
				 <IOPS>4350.916539</IOPS>
				 <IOPS_Read>2723.441257</IOPS_Read>
				 <IOPS_Write>1627.475282</IOPS_Write>
				 <Bytes_Transferred>59718656.000000</Bytes_Transferred>
				 <Bytes_Transferred_Read>36315136.000000</Bytes_Transferred_Read>
				 <Bytes_Transferred_Write>23403520.000000</Bytes_Transferred_Write>
				 <Bandwidth>37124001.721861</Bandwidth>
				 <Bandwidth_Read>22575243.009381</Bandwidth_Read>
				 <Bandwidth_Write>14548758.712480</Bandwidth_Write>
				 <Device_Response_Time>78390</Device_Response_Time>
				 <Min_Device_Response_Time>7</Min_Device_Response_Time>
				 <Max_Device_Response_Time>186821</Max_Device_Response_Time>
				 <End_to_End_Request_Delay>202647</End_to_End_Request_Delay>
				 <Min_End_to_End_Request_Delay>7</Min_End_to_End_Request_Delay>
				 <Max_End_to_End_Request_Delay>516829</Max_End_to_End_Request_Delay>
		</Host.IO_Flow>
	</Host>
	<SSDDevice>
		<SSDDevice.HostInterface>
				 <Name>SSDDevice.HostInterface</Name>
			<SSDDevice.IO_Stream>
					 <Stream_ID>0</Stream_ID>
					 <Average_Read_Transaction_Turnaround_Time>990</Average_Read_Transaction_Turnaround_Time>
					 <Average_Read_Transaction_Execution_Time>74</Average_Read_Transaction_Execution_Time>
					 <Average_Read_Transaction_Transfer_Time>13</Average_Read_Transaction_Transfer_Time>
					 <Average_Read_Transaction_Waiting_Time>902</Average_Read_Transaction_Waiting_Time>
					 <Average_Write_Transaction_Turnaround_Time>116689</Average_Write_Transaction_Turnaround_Time>
					 <Average_Write_Transaction_Execution_Time>728</Average_Write_Transaction_Execution_Time>
					 <Average_Write_Transaction_Transfer_Time>13</Average_Write_Transaction_Transfer_Time>
					 <Average_Write_Transaction_Waiting_Time>115947</Average_Write_Transaction_Waiting_Time>
			</SSDDevice.IO_Stream>
		</SSDDevice.HostInterface>
		<SSDDevice.FTL Issued_Flash_Read_CMD="15062" Issued_Flash_Interleaved_Read_CMD="0" Issued_Flash_Multiplane_Read_CMD="298" Issued_Flash_Copyback_Read_CMD="0" Issued_Flash_Multiplane_Copyback_Read_CMD="0" Issued_Flash_Program_CMD="4756" Issued_Flash_Interleaved_Program_CMD="0" Issued_Flash_Multiplane_Program_CMD="172" Issued_Flash_Interleaved_Multiplane_Program_CMD="0" Issued_Flash_Copyback_Program_CMD="0" Issued_Flash_Multiplane_Copyback_Program_CMD="0" Issued_Flash_Erase_CMD="0" Issued_Flash_Interleaved_Erase_CMD="0" Issued_Flash_Multiplane_Erase_CMD="0" Issued_Flash_Interleaved_Multiplane_Erase_CMD="0" Issued_Flash_Suspend_Program_CMD="0" Issued_Flash_Suspend_Erase_CMD="0" Issued_Flash_Read_CMD_For_Mapping="7203" Issued_Flash_Program_CMD_For_Mapping="0" CMT_Hits="59" CMT_Hits_For_Read="56" CMT_Hits_For_Write="3" CMT_Misses="0" CMT_Misses_For_Read="8396" CMT_Misses_For_Write="5097" Total_CMT_Queries="13552" Total_CMT_Queries_For_Reads="8452" Total_CMT_Queries_For_Writes="5100" Total_GC_Executions="0" Average_Page_Movement_For_GC="nan" Total_WL_Executions="0" Average_Page_Movement_For_WL="nan"/>
		<SSDDevice.TSU>
			<SSDDevice.TSU.User_Read_TR_Queue.Priority.URGENT Name="User_Read_TR_Queue@0@0@URGENT" No_Of_Transactions_Enqueued="0" No_Of_Transactions_Dequeued="0" Avg_Queue_Length="0.000000" Max_Queue_Length="0" STDev_Queue_Length="0.000000" Avg_Transaction_Waiting_Time="0" Max_Transaction_Waiting_Time="0"/>
			<SSDDevice.TSU.User_Read_TR_Queue.Priority.HIGH Name="User_Read_TR_Queue@0@0@HIGH" No_Of_Transactions_Enqueued="1055" No_Of_Transactions_Dequeued="1055" Avg_Queue_Length="0.392600" Max_Queue_Length="30" STDev_Queue_Length="2.117497" Avg_Transaction_Waiting_Time="598" Max_Transaction_Waiting_Time="4096"/>
			<SSDDevice.TSU.User_Read_TR_Queue.Priority.MEDIUM Name="User_Read_TR_Queue@0@0@MEDIUM" No_Of_Transactions_Enqueued="0" No_Of_Transactions_Dequeued="0" Avg_Queue_Length="0.000000" Max_Queue_Length="0" STDev_Queue_Length="0.000000" Avg_Transaction_Waiting_Time="0" Max_Transaction_Waiting_Time="0"/>
			<SSDDevice.TSU.User_Read_TR_Queue.Priority.LOW Name="User_Read_TR_Queue@0@0@LOW" No_Of_Transactions_Enqueued="0" No_Of_Transactions_Dequeued="0" Avg_Queue_Length="0.000000" Max_Queue_Length="0" STDev_Queue_Length="0.000000" Avg_Transaction_Waiting_Time="0" Max_Transaction_Waiting_Time="0"/>
			<SSDDevice.TSU.User_Read_TR_Queue.Priority.URGENT Name="User_Read_TR_Queue@0@1@URGENT" No_Of_Transactions_Enqueued="0" No_Of_Transactions_Dequeued="0" Avg_Queue_Length="0.000000" Max_Queue_Length="0" STDev_Queue_Length="0.000000" Avg_Transaction_Waiting_Time="0" Max_Transaction_Waiting_Time="0"/>
			<SSDDevice.TSU.User_Read_TR_Queue.Priority.HIGH Name="User_Read_TR_Queue@0@1@HIGH" No_Of_Transactions_Enqueued="1067" No_Of_Transactions_Dequeued="1067" Avg_Queue_Length="0.556316" Max_Queue_Length="43" STDev_Queue_Length="3.607949" Avg_Transaction_Waiting_Time="838" Max_Transaction_Waiting_Time="6144"/>
			<SSDDevice.TSU.User_Read_TR_Queue.Priority.MEDIUM Name="User_Read_TR_Queue@0@1@MEDIUM" No_Of_Transactions_Enqueued="0" No_Of_Transactions_Dequeued="0" Avg_Queue_Length="0.000000" Max_Queue_Length="0" STDev_Queue_Length="0.000000" Avg_Transaction_Waiting_Time="0" Max_Transaction_Waiting_Time="0"/>
			<SSDDevice.TSU.User_Read_TR_Queue.Priority.LOW Name="User_Read_TR_Queue@0@1@LOW" No_Of_Transactions_Enqueued="0" No_Of_Transactions_Dequeued="0" Avg_Queue_Length="0.000000" Max_Queue_Length="0" STDev_Queue_Length="0.000000" Avg_Transaction_Waiting_Time="0" Max_Transaction_Waiting_Time="0"/>
			<SSDDevice.TSU.User_Read_TR_Queue.Priority.URGENT Name="User_Read_TR_Queue@1@0@URGENT" No_Of_Transactions_Enqueued="0" No_Of_Transactions_Dequeued="0" Avg_Queue_Length="0.000000" Max_Queue_Length="0" STDev_Queue_Length="0.000000" Avg_Transaction_Waiting_Time="0" Max_Transaction_Waiting_Time="0"/>
			<SSDDevice.TSU.User_Read_TR_Queue.Priority.HIGH Name="User_Read_TR_Queue@1@0@HIGH" No_Of_Transactions_Enqueued="1026" No_Of_Transactions_Dequeued="1026" Avg_Queue_Length="0.286988" Max_Queue_Length="12" STDev_Queue_Length="0.959625" Avg_Transaction_Waiting_Time="449" Max_Transaction_Waiting_Time="1746"/>
			<SSDDevice.TSU.User_Read_TR_Queue.Priority.MEDIUM Name="User_Read_TR_Queue@1@0@MEDIUM" No_Of_Transactions_Enqueued="0" No_Of_Transactions_Dequeued="0" Avg_Queue_Length="0.000000" Max_Queue_Length="0" STDev_Queue_Length="0.000000" Avg_Transaction_Waiting_Time="0" Max_Transaction_Waiting_Time="0"/>
			<SSDDevice.TSU.User_Read_TR_Queue.Priority.LOW Name="User_Read_TR_Queue@1@0@LOW" No_Of_Transactions_Enqueued="0" No_Of_Transactions_Dequeued="0" Avg_Queue_Length="0.000000" Max_Queue_Length="0" STDev_Queue_Length="0.000000" Avg_Transaction_Waiting_Time="0" Max_Transaction_Waiting_Time="0"/>
			<SSDDevice.TSU.User_Read_TR_Queue.Priority.URGENT Name="User_Read_TR_Queue@1@1@URGENT" No_Of_Transactions_Enqueued="0" No_Of_Transactions_Dequeued="0" Avg_Queue_Length="0.000000" Max_Queue_Length="0" STDev_Queue_Length="0.000000" Avg_Transaction_Waiting_Time="0" Max_Transaction_Waiting_Time="0"/>
			<SSDDevice.TSU.User_Read_TR_Queue.Priority.HIGH Name="User_Read_TR_Queue@1@1@HIGH" No_Of_Transactions_Enqueued="1110" No_Of_Transactions_Dequeued="1110" Avg_Queue_Length="0.382975" Max_Queue_Length="23" STDev_Queue_Length="1.800759" Avg_Transaction_Waiting_Time="555" Max_Transaction_Waiting_Time="3126"/>
			<SSDDevice.TSU.User_Read_TR_Queue.Priority.MEDIUM Name="User_Read_TR_Queue@1@1@MEDIUM" No_Of_Transactions_Enqueued="0" No_Of_Transactions_Dequeued="0" Avg_Queue_Length="0.000000" Max_Queue_Length="0" STDev_Queue_Length="0.000000" Avg_Transaction_Waiting_Time="0" Max_Transaction_Waiting_Time="0"/>
			<SSDDevice.TSU.User_Read_TR_Queue.Priority.LOW Name="User_Read_TR_Queue@1@1@LOW" No_Of_Transactions_Enqueued="0" No_Of_Transactions_Dequeued="0" Avg_Queue_Length="0.000000" Max_Queue_Length="0" STDev_Queue_Length="0.000000" Avg_Transaction_Waiting_Time="0" Max_Transaction_Waiting_Time="0"/>
			<SSDDevice.TSU.User_Read_TR_Queue.Priority.URGENT Name="User_Read_TR_Queue@2@0@URGENT" No_Of_Transactions_Enqueued="0" No_Of_Transactions_Dequeued="0" Avg_Queue_Length="0.000000" Max_Queue_Length="0" STDev_Queue_Length="0.000000" Avg_Transaction_Waiting_Time="0" Max_Transaction_Waiting_Time="0"/>
			<SSDDevice.TSU.User_Read_TR_Queue.Priority.HIGH Name="User_Read_TR_Queue@2@0@HIGH" No_Of_Transactions_Enqueued="1034" No_Of_Transactions_Dequeued="1034" Avg_Queue_Length="0.297532" Max_Queue_Length="16" STDev_Queue_Length="1.159052" Avg_Transaction_Waiting_Time="462" Max_Transaction_Waiting_Time="1771"/>
			<SSDDevice.TSU.User_Read_TR_Queue.Priority.MEDIUM Name="User_Read_TR_Queue@2@0@MEDIUM" No_Of_Transactions_Enqueued="0" No_Of_Transactions_Dequeued="0" Avg_Queue_Length="0.000000" Max_Queue_Length="0" STDev_Queue_Length="0.000000" Avg_Transaction_Waiting_Time="0" Max_Transaction_Waiting_Time="0"/>
			<SSDDevice.TSU.User_Read_TR_Queue.Priority.LOW Name="User_Read_TR_Queue@2@0@LOW" No_Of_Transactions_Enqueued="0" No_Of_Transactions_Dequeued="0" Avg_Queue_Length="0.000000" Max_Queue_Length="0" STDev_Queue_Length="0.000000" Avg_Transaction_Waiting_Time="0" Max_Transaction_Waiting_Time="0"/>
			<SSDDevice.TSU.User_Read_TR_Queue.Priority.URGENT Name="User_Read_TR_Queue@2@1@URGENT" No_Of_Transactions_Enqueued="0" No_Of_Transactions_Dequeued="0" Avg_Queue_Length="0.000000" Max_Queue_Length="0" STDev_Queue_Length="0.000000" Avg_Transaction_Waiting_Time="0" Max_Transaction_Waiting_Time="0"/>
			<SSDDevice.TSU.User_Read_TR_Queue.Priority.HIGH Name="User_Read_TR_Queue@2@1@HIGH" No_Of_Transactions_Enqueued="1063" No_Of_Transactions_Dequeued="1063" Avg_Queue_Length="0.332894" Max_Queue_Length="19" STDev_Queue_Length="1.417666" Avg_Transaction_Waiting_Time="503" Max_Transaction_Waiting_Time="2230"/>
			<SSDDevice.TSU.User_Read_TR_Queue.Priority.MEDIUM Name="User_Read_TR_Queue@2@1@MEDIUM" No_Of_Transactions_Enqueued="0" No_Of_Transactions_Dequeued="0" Avg_Queue_Length="0.000000" Max_Queue_Length="0" STDev_Queue_Length="0.000000" Avg_Transaction_Waiting_Time="0" Max_Transaction_Waiting_Time="0"/>
			<SSDDevice.TSU.User_Read_TR_Queue.Priority.LOW Name="User_Read_TR_Queue@2@1@LOW" No_Of_Transactions_Enqueued="0" No_Of_Transactions_Dequeued="0" Avg_Queue_Length="0.000000" Max_Queue_Length="0" STDev_Queue_Length="0.000000" Avg_Transaction_Waiting_Time="0" Max_Transaction_Waiting_Time="0"/>
			<SSDDevice.TSU.User_Read_TR_Queue.Priority.URGENT Name="User_Read_TR_Queue@3@0@URGENT" No_Of_Transactions_Enqueued="0" No_Of_Transactions_Dequeued="0" Avg_Queue_Length="0.000000" Max_Queue_Length="0" STDev_Queue_Length="0.000000" Avg_Transaction_Waiting_Time="0" Max_Transaction_Waiting_Time="0"/>
			<SSDDevice.TSU.User_Read_TR_Queue.Priority.HIGH Name="User_Read_TR_Queue@3@0@HIGH" No_Of_Transactions_Enqueued="994" No_Of_Transactions_Dequeued="994" Avg_Queue_Length="0.289906" Max_Queue_Length="18" STDev_Queue_Length="1.200702" Avg_Transaction_Waiting_Time="469" Max_Transaction_Waiting_Time="1582"/>
			<SSDDevice.TSU.User_Read_TR_Queue.Priority.MEDIUM Name="User_Read_TR_Queue@3@0@MEDIUM" No_Of_Transactions_Enqueued="0" No_Of_Transactions_Dequeued="0" Avg_Queue_Length="0.000000" Max_Queue_Length="0" STDev_Queue_Length="0.000000" Avg_Transaction_Waiting_Time="0" Max_Transaction_Waiting_Time="0"/>
			<SSDDevice.TSU.User_Read_TR_Queue.Priority.LOW Name="User_Read_TR_Queue@3@0@LOW" No_Of_Transactions_Enqueued="0" No_Of_Transactions_Dequeued="0" Avg_Queue_Length="0.000000" Max_Queue_Length="0" STDev_Queue_Length="0.000000" Avg_Transaction_Waiting_Time="0" Max_Transaction_Waiting_Time="0"/>
			<SSDDevice.TSU.User_Read_TR_Queue.Priority.URGENT Name="User_Read_TR_Queue@3@1@URGENT" No_Of_Transactions_Enqueued="0" No_Of_Transactions_Dequeued="0" Avg_Queue_Length="0.000000" Max_Queue_Length="0" STDev_Queue_Length="0.000000" Avg_Transaction_Waiting_Time="0" Max_Transaction_Waiting_Time="0"/>
			<SSDDevice.TSU.User_Read_TR_Queue.Priority.HIGH Name="User_Read_TR_Queue@3@1@HIGH" No_Of_Transactions_Enqueued="1106" No_Of_Transactions_Dequeued="1106" Avg_Queue_Length="0.387071" Max_Queue_Length="31" STDev_Queue_Length="2.124138" Avg_Transaction_Waiting_Time="562" Max_Transaction_Waiting_Time="3625"/>
			<SSDDevice.TSU.User_Read_TR_Queue.Priority.MEDIUM Name="User_Read_TR_Queue@3@1@MEDIUM" No_Of_Transactions_Enqueued="0" No_Of_Transactions_Dequeued="0" Avg_Queue_Length="0.000000" Max_Queue_Length="0" STDev_Queue_Length="0.000000" Avg_Transaction_Waiting_Time="0" Max_Transaction_Waiting_Time="0"/>
			<SSDDevice.TSU.User_Read_TR_Queue.Priority.LOW Name="User_Read_TR_Queue@3@1@LOW" No_Of_Transactions_Enqueued="0" No_Of_Transactions_Dequeued="0" Avg_Queue_Length="0.000000" Max_Queue_Length="0" STDev_Queue_Length="0.000000" Avg_Transaction_Waiting_Time="0" Max_Transaction_Waiting_Time="0"/>
			<SSDDevice.TSU.User_Write_TR_Queue.Priority.URGENT Name="User_Write_TR_Queue@0@0@URGENT" No_Of_Transactions_Enqueued="0" No_Of_Transactions_Dequeued="0" Avg_Queue_Length="0.000000" Max_Queue_Length="0" STDev_Queue_Length="0.000000" Avg_Transaction_Waiting_Time="0" Max_Transaction_Waiting_Time="0"/>
			<SSDDevice.TSU.User_Write_TR_Queue.Priority.HIGH Name="User_Write_TR_Queue@0@0@HIGH" No_Of_Transactions_Enqueued="615" No_Of_Transactions_Dequeued="615" Avg_Queue_Length="1.249360" Max_Queue_Length="9" STDev_Queue_Length="3.563757" Avg_Transaction_Waiting_Time="3267" Max_Transaction_Waiting_Time="28642"/>
			<SSDDevice.TSU.User_Write_TR_Queue.Priority.MEDIUM Name="User_Write_TR_Queue@0@0@MEDIUM" No_Of_Transactions_Enqueued="0" No_Of_Transactions_Dequeued="0" Avg_Queue_Length="0.000000" Max_Queue_Length="0" STDev_Queue_Length="0.000000" Avg_Transaction_Waiting_Time="0" Max_Transaction_Waiting_Time="0"/>
			<SSDDevice.TSU.User_Write_TR_Queue.Priority.LOW Name="User_Write_TR_Queue@0@0@LOW" No_Of_Transactions_Enqueued="0" No_Of_Transactions_Dequeued="0" Avg_Queue_Length="0.000000" Max_Queue_Length="0" STDev_Queue_Length="0.000000" Avg_Transaction_Waiting_Time="0" Max_Transaction_Waiting_Time="0"/>
			<SSDDevice.TSU.User_Write_TR_Queue.Priority.URGENT Name="User_Write_TR_Queue@0@1@URGENT" No_Of_Transactions_Enqueued="0" No_Of_Transactions_Dequeued="0" Avg_Queue_Length="0.000000" Max_Queue_Length="0" STDev_Queue_Length="0.000000" Avg_Transaction_Waiting_Time="0" Max_Transaction_Waiting_Time="0"/>
			<SSDDevice.TSU.User_Write_TR_Queue.Priority.HIGH Name="User_Write_TR_Queue@0@1@HIGH" No_Of_Transactions_Enqueued="705" No_Of_Transactions_Dequeued="705" Avg_Queue_Length="4.431630" Max_Queue_Length="27" STDev_Queue_Length="22.620954" Avg_Transaction_Waiting_Time="10111" Max_Transaction_Waiting_Time="35584"/>
			<SSDDevice.TSU.User_Write_TR_Queue.Priority.MEDIUM Name="User_Write_TR_Queue@0@1@MEDIUM" No_Of_Transactions_Enqueued="0" No_Of_Transactions_Dequeued="0" Avg_Queue_Length="0.000000" Max_Queue_Length="0" STDev_Queue_Length="0.000000" Avg_Transaction_Waiting_Time="0" Max_Transaction_Waiting_Time="0"/>
			<SSDDevice.TSU.User_Write_TR_Queue.Priority.LOW Name="User_Write_TR_Queue@0@1@LOW" No_Of_Transactions_Enqueued="0" No_Of_Transactions_Dequeued="0" Avg_Queue_Length="0.000000" Max_Queue_Length="0" STDev_Queue_Length="0.000000" Avg_Transaction_Waiting_Time="0" Max_Transaction_Waiting_Time="0"/>
			<SSDDevice.TSU.User_Write_TR_Queue.Priority.URGENT Name="User_Write_TR_Queue@1@0@URGENT" No_Of_Transactions_Enqueued="0" No_Of_Transactions_Dequeued="0" Avg_Queue_Length="0.000000" Max_Queue_Length="0" STDev_Queue_Length="0.000000" Avg_Transaction_Waiting_Time="0" Max_Transaction_Waiting_Time="0"/>
			<SSDDevice.TSU.User_Write_TR_Queue.Priority.HIGH Name="User_Write_TR_Queue@1@0@HIGH" No_Of_Transactions_Enqueued="623" No_Of_Transactions_Dequeued="623" Avg_Queue_Length="1.832192" Max_Queue_Length="11" STDev_Queue_Length="5.828783" Avg_Transaction_Waiting_Time="4730" Max_Transaction_Waiting_Time="30974"/>
			<SSDDevice.TSU.User_Write_TR_Queue.Priority.MEDIUM Name="User_Write_TR_Queue@1@0@MEDIUM" No_Of_Transactions_Enqueued="0" No_Of_Transactions_Dequeued="0" Avg_Queue_Length="0.000000" Max_Queue_Length="0" STDev_Queue_Length="0.000000" Avg_Transaction_Waiting_Time="0" Max_Transaction_Waiting_Time="0"/>
			<SSDDevice.TSU.User_Write_TR_Queue.Priority.LOW Name="User_Write_TR_Queue@1@0@LOW" No_Of_Transactions_Enqueued="0" No_Of_Transactions_Dequeued="0" Avg_Queue_Length="0.000000" Max_Queue_Length="0" STDev_Queue_Length="0.000000" Avg_Transaction_Waiting_Time="0" Max_Transaction_Waiting_Time="0"/>
			<SSDDevice.TSU.User_Write_TR_Queue.Priority.URGENT Name="User_Write_TR_Queue@1@1@URGENT" No_Of_Transactions_Enqueued="0" No_Of_Transactions_Dequeued="0" Avg_Queue_Length="0.000000" Max_Queue_Length="0" STDev_Queue_Length="0.000000" Avg_Transaction_Waiting_Time="0" Max_Transaction_Waiting_Time="0"/>
			<SSDDevice.TSU.User_Write_TR_Queue.Priority.HIGH Name="User_Write_TR_Queue@1@1@HIGH" No_Of_Transactions_Enqueued="650" No_Of_Transactions_Dequeued="650" Avg_Queue_Length="4.868378" Max_Queue_Length="26" STDev_Queue_Length="24.366342" Avg_Transaction_Waiting_Time="12048" Max_Transaction_Waiting_Time="33710"/>
			<SSDDevice.TSU.User_Write_TR_Queue.Priority.MEDIUM Name="User_Write_TR_Queue@1@1@MEDIUM" No_Of_Transactions_Enqueued="0" No_Of_Transactions_Dequeued="0" Avg_Queue_Length="0.000000" Max_Queue_Length="0" STDev_Queue_Length="0.000000" Avg_Transaction_Waiting_Time="0" Max_Transaction_Waiting_Time="0"/>
			<SSDDevice.TSU.User_Write_TR_Queue.Priority.LOW Name="User_Write_TR_Queue@1@1@LOW" No_Of_Transactions_Enqueued="0" No_Of_Transactions_Dequeued="0" Avg_Queue_Length="0.000000" Max_Queue_Length="0" STDev_Queue_Length="0.000000" Avg_Transaction_Waiting_Time="0" Max_Transaction_Waiting_Time="0"/>
			<SSDDevice.TSU.User_Write_TR_Queue.Priority.URGENT Name="User_Write_TR_Queue@2@0@URGENT" No_Of_Transactions_Enqueued="0" No_Of_Transactions_Dequeued="0" Avg_Queue_Length="0.000000" Max_Queue_Length="0" STDev_Queue_Length="0.000000" Avg_Transaction_Waiting_Time="0" Max_Transaction_Waiting_Time="0"/>
			<SSDDevice.TSU.User_Write_TR_Queue.Priority.HIGH Name="User_Write_TR_Queue@2@0@HIGH" No_Of_Transactions_Enqueued="628" No_Of_Transactions_Dequeued="628" Avg_Queue_Length="1.670480" Max_Queue_Length="14" STDev_Queue_Length="6.043309" Avg_Transaction_Waiting_Time="4278" Max_Transaction_Waiting_Time="25759"/>
			<SSDDevice.TSU.User_Write_TR_Queue.Priority.MEDIUM Name="User_Write_TR_Queue@2@0@MEDIUM" No_Of_Transactions_Enqueued="0" No_Of_Transactions_Dequeued="0" Avg_Queue_Length="0.000000" Max_Queue_Length="0" STDev_Queue_Length="0.000000" Avg_Transaction_Waiting_Time="0" Max_Transaction_Waiting_Time="0"/>
			<SSDDevice.TSU.User_Write_TR_Queue.Priority.LOW Name="User_Write_TR_Queue@2@0@LOW" No_Of_Transactions_Enqueued="0" No_Of_Transactions_Dequeued="0" Avg_Queue_Length="0.000000" Max_Queue_Length="0" STDev_Queue_Length="0.000000" Avg_Transaction_Waiting_Time="0" Max_Transaction_Waiting_Time="0"/>
			<SSDDevice.TSU.User_Write_TR_Queue.Priority.URGENT Name="User_Write_TR_Queue@2@1@URGENT" No_Of_Transactions_Enqueued="0" No_Of_Transactions_Dequeued="0" Avg_Queue_Length="0.000000" Max_Queue_Length="0" STDev_Queue_Length="0.000000" Avg_Transaction_Waiting_Time="0" Max_Transaction_Waiting_Time="0"/>
			<SSDDevice.TSU.User_Write_TR_Queue.Priority.HIGH Name="User_Write_TR_Queue@2@1@HIGH" No_Of_Transactions_Enqueued="597" No_Of_Transactions_Dequeued="597" Avg_Queue_Length="1.604991" Max_Queue_Length="17" STDev_Queue_Length="6.435123" Avg_Transaction_Waiting_Time="4324" Max_Transaction_Waiting_Time="28827"/>
			<SSDDevice.TSU.User_Write_TR_Queue.Priority.MEDIUM Name="User_Write_TR_Queue@2@1@MEDIUM" No_Of_Transactions_Enqueued="0" No_Of_Transactions_Dequeued="0" Avg_Queue_Length="0.000000" Max_Queue_Length="0" STDev_Queue_Length="0.000000" Avg_Transaction_Waiting_Time="0" Max_Transaction_Waiting_Time="0"/>
			<SSDDevice.TSU.User_Write_TR_Queue.Priority.LOW Name="User_Write_TR_Queue@2@1@LOW" No_Of_Transactions_Enqueued="0" No_Of_Transactions_Dequeued="0" Avg_Queue_Length="0.000000" Max_Queue_Length="0" STDev_Queue_Length="0.000000" Avg_Transaction_Waiting_Time="0" Max_Transaction_Waiting_Time="0"/>
			<SSDDevice.TSU.User_Write_TR_Queue.Priority.URGENT Name="User_Write_TR_Queue@3@0@URGENT" No_Of_Transactions_Enqueued="0" No_Of_Transactions_Dequeued="0" Avg_Queue_Length="0.000000" Max_Queue_Length="0" STDev_Queue_Length="0.000000" Avg_Transaction_Waiting_Time="0" Max_Transaction_Waiting_Time="0"/>
			<SSDDevice.TSU.User_Write_TR_Queue.Priority.HIGH Name="User_Write_TR_Queue@3@0@HIGH" No_Of_Transactions_Enqueued="654" No_Of_Transactions_Dequeued="654" Avg_Queue_Length="1.925998" Max_Queue_Length="15" STDev_Queue_Length="7.229352" Avg_Transaction_Waiting_Time="4737" Max_Transaction_Waiting_Time="29685"/>
			<SSDDevice.TSU.User_Write_TR_Queue.Priority.MEDIUM Name="User_Write_TR_Queue@3@0@MEDIUM" No_Of_Transactions_Enqueued="0" No_Of_Transactions_Dequeued="0" Avg_Queue_Length="0.000000" Max_Queue_Length="0" STDev_Queue_Length="0.000000" Avg_Transaction_Waiting_Time="0" Max_Transaction_Waiting_Time="0"/>
			<SSDDevice.TSU.User_Write_TR_Queue.Priority.LOW Name="User_Write_TR_Queue@3@0@LOW" No_Of_Transactions_Enqueued="0" No_Of_Transactions_Dequeued="0" Avg_Queue_Length="0.000000" Max_Queue_Length="0" STDev_Queue_Length="0.000000" Avg_Transaction_Waiting_Time="0" Max_Transaction_Waiting_Time="0"/>
			<SSDDevice.TSU.User_Write_TR_Queue.Priority.URGENT Name="User_Write_TR_Queue@3@1@URGENT" No_Of_Transactions_Enqueued="0" No_Of_Transactions_Dequeued="0" Avg_Queue_Length="0.000000" Max_Queue_Length="0" STDev_Queue_Length="0.000000" Avg_Transaction_Waiting_Time="0" Max_Transaction_Waiting_Time="0"/>
			<SSDDevice.TSU.User_Write_TR_Queue.Priority.HIGH Name="User_Write_TR_Queue@3@1@HIGH" No_Of_Transactions_Enqueued="628" No_Of_Transactions_Dequeued="628" Avg_Queue_Length="3.006948" Max_Queue_Length="22" STDev_Queue_Length="13.799895" Avg_Transaction_Waiting_Time="7702" Max_Transaction_Waiting_Time="33241"/>
			<SSDDevice.TSU.User_Write_TR_Queue.Priority.MEDIUM Name="User_Write_TR_Queue@3@1@MEDIUM" No_Of_Transactions_Enqueued="0" No_Of_Transactions_Dequeued="0" Avg_Queue_Length="0.000000" Max_Queue_Length="0" STDev_Queue_Length="0.000000" Avg_Transaction_Waiting_Time="0" Max_Transaction_Waiting_Time="0"/>
			<SSDDevice.TSU.User_Write_TR_Queue.Priority.LOW Name="User_Write_TR_Queue@3@1@LOW" No_Of_Transactions_Enqueued="0" No_Of_Transactions_Dequeued="0" Avg_Queue_Length="0.000000" Max_Queue_Length="0" STDev_Queue_Length="0.000000" Avg_Transaction_Waiting_Time="0" Max_Transaction_Waiting_Time="0"/>
			<SSDDevice.TSU.Mapping_Read_TR_Queue Name="Mapping_Read_TR_Queue@0@0" No_Of_Transactions_Enqueued="885" No_Of_Transactions_Dequeued="885" Avg_Queue_Length="0.153643" Max_Queue_Length="6" STDev_Queue_Length="0.357232" Avg_Transaction_Waiting_Time="279" Max_Transaction_Waiting_Time="813"/>
			<SSDDevice.TSU.Mapping_Read_TR_Queue Name="Mapping_Read_TR_Queue@0@1" No_Of_Transactions_Enqueued="894" No_Of_Transactions_Dequeued="894" Avg_Queue_Length="0.161571" Max_Queue_Length="5" STDev_Queue_Length="0.338935" Avg_Transaction_Waiting_Time="290" Max_Transaction_Waiting_Time="833"/>
			<SSDDevice.TSU.Mapping_Read_TR_Queue Name="Mapping_Read_TR_Queue@1@0" No_Of_Transactions_Enqueued="957" No_Of_Transactions_Dequeued="957" Avg_Queue_Length="0.177025" Max_Queue_Length="8" STDev_Queue_Length="0.481754" Avg_Transaction_Waiting_Time="297" Max_Transaction_Waiting_Time="837"/>
			<SSDDevice.TSU.Mapping_Read_TR_Queue Name="Mapping_Read_TR_Queue@1@1" No_Of_Transactions_Enqueued="915" No_Of_Transactions_Dequeued="915" Avg_Queue_Length="0.160362" Max_Queue_Length="5" STDev_Queue_Length="0.336765" Avg_Transaction_Waiting_Time="281" Max_Transaction_Waiting_Time="829"/>
			<SSDDevice.TSU.Mapping_Read_TR_Queue Name="Mapping_Read_TR_Queue@2@0" No_Of_Transactions_Enqueued="855" No_Of_Transactions_Dequeued="855" Avg_Queue_Length="0.151999" Max_Queue_Length="5" STDev_Queue_Length="0.319289" Avg_Transaction_Waiting_Time="285" Max_Transaction_Waiting_Time="846"/>
			<SSDDevice.TSU.Mapping_Read_TR_Queue Name="Mapping_Read_TR_Queue@2@1" No_Of_Transactions_Enqueued="843" No_Of_Transactions_Dequeued="843" Avg_Queue_Length="0.135715" Max_Queue_Length="5" STDev_Queue_Length="0.285880" Avg_Transaction_Waiting_Time="258" Max_Transaction_Waiting_Time="824"/>
			<SSDDevice.TSU.Mapping_Read_TR_Queue Name="Mapping_Read_TR_Queue@3@0" No_Of_Transactions_Enqueued="931" No_Of_Transactions_Dequeued="931" Avg_Queue_Length="0.165676" Max_Queue_Length="5" STDev_Queue_Length="0.346826" Avg_Transaction_Waiting_Time="286" Max_Transaction_Waiting_Time="819"/>
			<SSDDevice.TSU.Mapping_Read_TR_Queue Name="Mapping_Read_TR_Queue@3@1" No_Of_Transactions_Enqueued="923" No_Of_Transactions_Dequeued="923" Avg_Queue_Length="0.155423" Max_Queue_Length="5" STDev_Queue_Length="0.326945" Avg_Transaction_Waiting_Time="270" Max_Transaction_Waiting_Time="901"/>
			<SSDDevice.TSU.Mapping_Write_TR_Queue Name="Mapping_Write_TR_Queue@0@0" No_Of_Transactions_Enqueued="0" No_Of_Transactions_Dequeued="0" Avg_Queue_Length="0.000000" Max_Queue_Length="0" STDev_Queue_Length="0.000000" Avg_Transaction_Waiting_Time="0" Max_Transaction_Waiting_Time="0"/>
			<SSDDevice.TSU.Mapping_Write_TR_Queue Name="Mapping_Write_TR_Queue@0@1" No_Of_Transactions_Enqueued="0" No_Of_Transactions_Dequeued="0" Avg_Queue_Length="0.000000" Max_Queue_Length="0" STDev_Queue_Length="0.000000" Avg_Transaction_Waiting_Time="0" Max_Transaction_Waiting_Time="0"/>
			<SSDDevice.TSU.Mapping_Write_TR_Queue Name="Mapping_Write_TR_Queue@1@0" No_Of_Transactions_Enqueued="0" No_Of_Transactions_Dequeued="0" Avg_Queue_Length="0.000000" Max_Queue_Length="0" STDev_Queue_Length="0.000000" Avg_Transaction_Waiting_Time="0" Max_Transaction_Waiting_Time="0"/>
			<SSDDevice.TSU.Mapping_Write_TR_Queue Name="Mapping_Write_TR_Queue@1@1" No_Of_Transactions_Enqueued="0" No_Of_Transactions_Dequeued="0" Avg_Queue_Length="0.000000" Max_Queue_Length="0" STDev_Queue_Length="0.000000" Avg_Transaction_Waiting_Time="0" Max_Transaction_Waiting_Time="0"/>
			<SSDDevice.TSU.Mapping_Write_TR_Queue Name="Mapping_Write_TR_Queue@2@0" No_Of_Transactions_Enqueued="0" No_Of_Transactions_Dequeued="0" Avg_Queue_Length="0.000000" Max_Queue_Length="0" STDev_Queue_Length="0.000000" Avg_Transaction_Waiting_Time="0" Max_Transaction_Waiting_Time="0"/>
			<SSDDevice.TSU.Mapping_Write_TR_Queue Name="Mapping_Write_TR_Queue@2@1" No_Of_Transactions_Enqueued="0" No_Of_Transactions_Dequeued="0" Avg_Queue_Length="0.000000" Max_Queue_Length="0" STDev_Queue_Length="0.000000" Avg_Transaction_Waiting_Time="0" Max_Transaction_Waiting_Time="0"/>
			<SSDDevice.TSU.Mapping_Write_TR_Queue Name="Mapping_Write_TR_Queue@3@0" No_Of_Transactions_Enqueued="0" No_Of_Transactions_Dequeued="0" Avg_Queue_Length="0.000000" Max_Queue_Length="0" STDev_Queue_Length="0.000000" Avg_Transaction_Waiting_Time="0" Max_Transaction_Waiting_Time="0"/>
			<SSDDevice.TSU.Mapping_Write_TR_Queue Name="Mapping_Write_TR_Queue@3@1" No_Of_Transactions_Enqueued="0" No_Of_Transactions_Dequeued="0" Avg_Queue_Length="0.000000" Max_Queue_Length="0" STDev_Queue_Length="0.000000" Avg_Transaction_Waiting_Time="0" Max_Transaction_Waiting_Time="0"/>
			<SSDDevice.TSU.GC_Read_TR_Queue Name="GC_Read_TR_Queue@0@0" No_Of_Transactions_Enqueued="0" No_Of_Transactions_Dequeued="0" Avg_Queue_Length="0.000000" Max_Queue_Length="0" STDev_Queue_Length="0.000000" Avg_Transaction_Waiting_Time="0" Max_Transaction_Waiting_Time="0"/>
			<SSDDevice.TSU.GC_Read_TR_Queue Name="GC_Read_TR_Queue@0@1" No_Of_Transactions_Enqueued="0" No_Of_Transactions_Dequeued="0" Avg_Queue_Length="0.000000" Max_Queue_Length="0" STDev_Queue_Length="0.000000" Avg_Transaction_Waiting_Time="0" Max_Transaction_Waiting_Time="0"/>
			<SSDDevice.TSU.GC_Read_TR_Queue Name="GC_Read_TR_Queue@1@0" No_Of_Transactions_Enqueued="0" No_Of_Transactions_Dequeued="0" Avg_Queue_Length="0.000000" Max_Queue_Length="0" STDev_Queue_Length="0.000000" Avg_Transaction_Waiting_Time="0" Max_Transaction_Waiting_Time="0"/>
			<SSDDevice.TSU.GC_Read_TR_Queue Name="GC_Read_TR_Queue@1@1" No_Of_Transactions_Enqueued="0" No_Of_Transactions_Dequeued="0" Avg_Queue_Length="0.000000" Max_Queue_Length="0" STDev_Queue_Length="0.000000" Avg_Transaction_Waiting_Time="0" Max_Transaction_Waiting_Time="0"/>
			<SSDDevice.TSU.GC_Read_TR_Queue Name="GC_Read_TR_Queue@2@0" No_Of_Transactions_Enqueued="0" No_Of_Transactions_Dequeued="0" Avg_Queue_Length="0.000000" Max_Queue_Length="0" STDev_Queue_Length="0.000000" Avg_Transaction_Waiting_Time="0" Max_Transaction_Waiting_Time="0"/>
			<SSDDevice.TSU.GC_Read_TR_Queue Name="GC_Read_TR_Queue@2@1" No_Of_Transactions_Enqueued="0" No_Of_Transactions_Dequeued="0" Avg_Queue_Length="0.000000" Max_Queue_Length="0" STDev_Queue_Length="0.000000" Avg_Transaction_Waiting_Time="0" Max_Transaction_Waiting_Time="0"/>
			<SSDDevice.TSU.GC_Read_TR_Queue Name="GC_Read_TR_Queue@3@0" No_Of_Transactions_Enqueued="0" No_Of_Transactions_Dequeued="0" Avg_Queue_Length="0.000000" Max_Queue_Length="0" STDev_Queue_Length="0.000000" Avg_Transaction_Waiting_Time="0" Max_Transaction_Waiting_Time="0"/>
			<SSDDevice.TSU.GC_Read_TR_Queue Name="GC_Read_TR_Queue@3@1" No_Of_Transactions_Enqueued="0" No_Of_Transactions_Dequeued="0" Avg_Queue_Length="0.000000" Max_Queue_Length="0" STDev_Queue_Length="0.000000" Avg_Transaction_Waiting_Time="0" Max_Transaction_Waiting_Time="0"/>
			<SSDDevice.TSU.GC_Write_TR_Queue Name="GC_Write_TR_Queue@0@0" No_Of_Transactions_Enqueued="0" No_Of_Transactions_Dequeued="0" Avg_Queue_Length="0.000000" Max_Queue_Length="0" STDev_Queue_Length="0.000000" Avg_Transaction_Waiting_Time="0" Max_Transaction_Waiting_Time="0"/>
			<SSDDevice.TSU.GC_Write_TR_Queue Name="GC_Write_TR_Queue@0@1" No_Of_Transactions_Enqueued="0" No_Of_Transactions_Dequeued="0" Avg_Queue_Length="0.000000" Max_Queue_Length="0" STDev_Queue_Length="0.000000" Avg_Transaction_Waiting_Time="0" Max_Transaction_Waiting_Time="0"/>
			<SSDDevice.TSU.GC_Write_TR_Queue Name="GC_Write_TR_Queue@1@0" No_Of_Transactions_Enqueued="0" No_Of_Transactions_Dequeued="0" Avg_Queue_Length="0.000000" Max_Queue_Length="0" STDev_Queue_Length="0.000000" Avg_Transaction_Waiting_Time="0" Max_Transaction_Waiting_Time="0"/>
			<SSDDevice.TSU.GC_Write_TR_Queue Name="GC_Write_TR_Queue@1@1" No_Of_Transactions_Enqueued="0" No_Of_Transactions_Dequeued="0" Avg_Queue_Length="0.000000" Max_Queue_Length="0" STDev_Queue_Length="0.000000" Avg_Transaction_Waiting_Time="0" Max_Transaction_Waiting_Time="0"/>
			<SSDDevice.TSU.GC_Write_TR_Queue Name="GC_Write_TR_Queue@2@0" No_Of_Transactions_Enqueued="0" No_Of_Transactions_Dequeued="0" Avg_Queue_Length="0.000000" Max_Queue_Length="0" STDev_Queue_Length="0.000000" Avg_Transaction_Waiting_Time="0" Max_Transaction_Waiting_Time="0"/>
			<SSDDevice.TSU.GC_Write_TR_Queue Name="GC_Write_TR_Queue@2@1" No_Of_Transactions_Enqueued="0" No_Of_Transactions_Dequeued="0" Avg_Queue_Length="0.000000" Max_Queue_Length="0" STDev_Queue_Length="0.000000" Avg_Transaction_Waiting_Time="0" Max_Transaction_Waiting_Time="0"/>
			<SSDDevice.TSU.GC_Write_TR_Queue Name="GC_Write_TR_Queue@3@0" No_Of_Transactions_Enqueued="0" No_Of_Transactions_Dequeued="0" Avg_Queue_Length="0.000000" Max_Queue_Length="0" STDev_Queue_Length="0.000000" Avg_Transaction_Waiting_Time="0" Max_Transaction_Waiting_Time="0"/>
			<SSDDevice.TSU.GC_Write_TR_Queue Name="GC_Write_TR_Queue@3@1" No_Of_Transactions_Enqueued="0" No_Of_Transactions_Dequeued="0" Avg_Queue_Length="0.000000" Max_Queue_Length="0" STDev_Queue_Length="0.000000" Avg_Transaction_Waiting_Time="0" Max_Transaction_Waiting_Time="0"/>
			<SSDDevice.TSU.GC_Erase_TR_Queue Name="GC_Erase_TR_Queue@0@0" No_Of_Transactions_Enqueued="0" No_Of_Transactions_Dequeued="0" Avg_Queue_Length="0.000000" Max_Queue_Length="0" STDev_Queue_Length="0.000000" Avg_Transaction_Waiting_Time="0" Max_Transaction_Waiting_Time="0"/>
			<SSDDevice.TSU.GC_Erase_TR_Queue Name="GC_Erase_TR_Queue@0@1" No_Of_Transactions_Enqueued="0" No_Of_Transactions_Dequeued="0" Avg_Queue_Length="0.000000" Max_Queue_Length="0" STDev_Queue_Length="0.000000" Avg_Transaction_Waiting_Time="0" Max_Transaction_Waiting_Time="0"/>
			<SSDDevice.TSU.GC_Erase_TR_Queue Name="GC_Erase_TR_Queue@1@0" No_Of_Transactions_Enqueued="0" No_Of_Transactions_Dequeued="0" Avg_Queue_Length="0.000000" Max_Queue_Length="0" STDev_Queue_Length="0.000000" Avg_Transaction_Waiting_Time="0" Max_Transaction_Waiting_Time="0"/>
			<SSDDevice.TSU.GC_Erase_TR_Queue Name="GC_Erase_TR_Queue@1@1" No_Of_Transactions_Enqueued="0" No_Of_Transactions_Dequeued="0" Avg_Queue_Length="0.000000" Max_Queue_Length="0" STDev_Queue_Length="0.000000" Avg_Transaction_Waiting_Time="0" Max_Transaction_Waiting_Time="0"/>
			<SSDDevice.TSU.GC_Erase_TR_Queue Name="GC_Erase_TR_Queue@2@0" No_Of_Transactions_Enqueued="0" No_Of_Transactions_Dequeued="0" Avg_Queue_Length="0.000000" Max_Queue_Length="0" STDev_Queue_Length="0.000000" Avg_Transaction_Waiting_Time="0" Max_Transaction_Waiting_Time="0"/>
			<SSDDevice.TSU.GC_Erase_TR_Queue Name="GC_Erase_TR_Queue@2@1" No_Of_Transactions_Enqueued="0" No_Of_Transactions_Dequeued="0" Avg_Queue_Length="0.000000" Max_Queue_Length="0" STDev_Queue_Length="0.000000" Avg_Transaction_Waiting_Time="0" Max_Transaction_Waiting_Time="0"/>
			<SSDDevice.TSU.GC_Erase_TR_Queue Name="GC_Erase_TR_Queue@3@0" No_Of_Transactions_Enqueued="0" No_Of_Transactions_Dequeued="0" Avg_Queue_Length="0.000000" Max_Queue_Length="0" STDev_Queue_Length="0.000000" Avg_Transaction_Waiting_Time="0" Max_Transaction_Waiting_Time="0"/>
			<SSDDevice.TSU.GC_Erase_TR_Queue Name="GC_Erase_TR_Queue@3@1" No_Of_Transactions_Enqueued="0" No_Of_Transactions_Dequeued="0" Avg_Queue_Length="0.000000" Max_Queue_Length="0" STDev_Queue_Length="0.000000" Avg_Transaction_Waiting_Time="0" Max_Transaction_Waiting_Time="0"/>
		</SSDDevice.TSU>
		<SSDDevice.FlashChips ID="@0@0" Fraction_of_Time_in_Execution="0.365460" Fraction_of_Time_in_DataXfer="0.014951" Fraction_of_Time_in_DataXfer_and_Execution="0.000000" Fraction_of_Time_Idle="0.985049"/>
		<SSDDevice.FlashChips ID="@0@1" Fraction_of_Time_in_Execution="0.396931" Fraction_of_Time_in_DataXfer="0.015436" Fraction_of_Time_in_DataXfer_and_Execution="0.000000" Fraction_of_Time_Idle="0.984564"/>
		<SSDDevice.FlashChips ID="@1@0" Fraction_of_Time_in_Execution="0.375764" Fraction_of_Time_in_DataXfer="0.015157" Fraction_of_Time_in_DataXfer_and_Execution="0.000000" Fraction_of_Time_Idle="0.984843"/>
		<SSDDevice.FlashChips ID="@1@1" Fraction_of_Time_in_Execution="0.390777" Fraction_of_Time_in_DataXfer="0.015945" Fraction_of_Time_in_DataXfer_and_Execution="0.000000" Fraction_of_Time_Idle="0.984055"/>
		<SSDDevice.FlashChips ID="@2@0" Fraction_of_Time_in_Execution="0.374178" Fraction_of_Time_in_DataXfer="0.014569" Fraction_of_Time_in_DataXfer_and_Execution="0.000000" Fraction_of_Time_Idle="0.985431"/>
		<SSDDevice.FlashChips ID="@2@1" Fraction_of_Time_in_Execution="0.355249" Fraction_of_Time_in_DataXfer="0.014509" Fraction_of_Time_in_DataXfer_and_Execution="0.000000" Fraction_of_Time_Idle="0.985491"/>
		<SSDDevice.FlashChips ID="@3@0" Fraction_of_Time_in_Execution="0.384575" Fraction_of_Time_in_DataXfer="0.014857" Fraction_of_Time_in_DataXfer_and_Execution="0.000000" Fraction_of_Time_Idle="0.985143"/>
		<SSDDevice.FlashChips ID="@3@1" Fraction_of_Time_in_Execution="0.371009" Fraction_of_Time_in_DataXfer="0.015735" Fraction_of_Time_in_DataXfer_and_Execution="0.000000" Fraction_of_Time_Idle="0.984265"/>
	</SSDDevice>
</MQSim_Results>
